README.rst
setup.py
testrail_client/__init__.py
testrail_client/client.py
testrail_client/api/__init__.py
testrail_client/api/base.py
testrail_client/api/case.py
testrail_client/api/configurations.py
testrail_client/api/error.py
testrail_client/api/milestone.py
testrail_client/api/plan.py
testrail_client/api/project.py
testrail_client/api/result.py
testrail_client/api/run.py
testrail_client/api/section.py
testrail_client/api/suite.py
testrail_client/api/test.py
testrail_client/api/user.py
testrail_lib.egg-info/PKG-INFO
testrail_lib.egg-info/SOURCES.txt
testrail_lib.egg-info/dependency_links.txt
testrail_lib.egg-info/requires.txt
testrail_lib.egg-info/top_level.txt