Metadata-Version: 1.1
Name: testrail-lib
Version: 0.1.1
Summary: Python client library for TestRail APIs (http)
Home-page: https://github.com/tonybearpan/testrail-lib
Author: tonybearpan
Author-email: tonybearpan@gmail.com
License: MIT License
Keywords: TestRail,TestRail API
Platform: any
Classifier: Environment :: Web Environment
Classifier: Intended Audience :: Developers
Classifier: License :: OSI Approved :: MIT License
Classifier: Operating System :: OS Independent
Classifier: Programming Language :: Python
Classifier: Topic :: Internet :: WWW/HTTP :: Dynamic Content
Classifier: Topic :: Software Development :: Libraries :: Python Modules
